{
  "schema_version": "radiology-evidence-review/v2",
  "claim_flags": {
    "clinical_claim": false,
    "clinical_validation_claim": false,
    "medical_device_claim": false,
    "regulatory_compliance_claim": false,
    "production_ready_claim": false,
    "sota_claim": false,
    "safety_certification_claim": false,
    "data_redistributed_in_repo": false
  },
  "review_scope": {
    "purpose": "publication boundary for the radiology reference profile",
    "public_role": "domain-adapter reference profile only",
    "aos_role": "control layer around model-output metadata",
    "radiology_product_claim": false
  },
  "current_public_evidence_status": {
    "performance_metrics_public": false,
    "current_domain_benchmark_public": false,
    "restricted_artifacts_public": false,
    "formal_integrity_material_public": false,
    "reason": "The public repository keeps radiology as a reference profile and does not publish current domain-performance metrics or restricted evidence summaries."
  },
  "allowed_public_use": [
    "reference profile explanation",
    "model-output to control-verdict separation",
    "human-review boundary explanation",
    "publication-safety boundary"
  ],
  "not_claimed": [
    "clinical validation",
    "diagnosis or treatment recommendation",
    "medical-device status",
    "regulatory approval",
    "production deployment readiness",
    "current radiology benchmark performance",
    "state-of-the-art performance",
    "production-grade signatures"
  ],
  "required_before_metrics_publication": [
    "dataset_name",
    "dataset_version",
    "source",
    "access_date",
    "terms_or_license",
    "split_definition",
    "sample_count",
    "metric_definitions",
    "baseline_definition",
    "run_date",
    "reproducibility_metadata",
    "non_claim_flags"
  ],
  "safe_public_summary": "Radiology is a reference profile for the AOS control pattern. This public repository does not publish current radiology performance metrics, clinical validation, production readiness, regulatory compliance, or specialist implementation material."
}
